wordsegmentation.py
corpus/bigrams.txt
corpus/filter.py
corpus/filter_1_2_letters.py
corpus/filtered_1_2_letter_only.txt
corpus/filtered_unigram_v1.txt
corpus/filtered_unigram_v2_allow_upper.txt
corpus/unigrams.txt
corpus/unigrams.txt.original
wordsegmentation-0.3.5.dist-info/DESCRIPTION.rst
wordsegmentation-0.3.5.dist-info/METADATA
wordsegmentation-0.3.5.dist-info/RECORD
wordsegmentation-0.3.5.dist-info/WHEEL
wordsegmentation-0.3.5.dist-info/metadata.json
wordsegmentation-0.3.5.dist-info/top_level.txt
