Metadata-Version: 2.0
Name: wordsegmentation
Version: 0.3.5
Summary: English word segmentation.
Home-page: UNKNOWN
Author: Weihan Jiang
Author-email: weihan.github@gmail.com
License: Copyright 2015 Weihan Jiang
Requires-Dist: networkx
